{
  "types": ["time_delay","document_timer","document_timer_once","document_timer_stop","element_event","element_event_stop","async_function","call_async_function","transform_async_function","text_to_number","loop_break","loop_continue","function_return","mouse_coordinate_get","music_create","music_delete","image_create","image_boundary","image_sys_get","image_collision","image_set","image_get","image_onclick_listener","image_onclick_do","image_onclick_get","image_boundary_collision","image_boundary_collision_do","image_delete","image_move","move_to_mouse","move_to_coordinate","image_resize","rotatez_degrees","rotate_vertical_flip","rotate_horizontal_flip","table_create","table_set","image_onclick_listener","table_td_onclick_do","table_get","table_clear","table_delete","table_td_insert_img","table_td_img_move","table_td_copy_move","table_td_img_get","image_onclick_get","table_td_insert_text","table_td_set","table_border_set","table_td_border_set","table_td_get","table_td_clear","canvas_create","canvas_line","canvas_rect","canvas_arc","canvas_img_url","canvas_img","canvas_text","canvas_clear","canvas_delete","image_onclick_listener","canvas_onclick_do","canvas_onclick_get","button_create","button_set","button_get","button_delete","image_onclick_listener","button_onclick_do","body_set"],
  "category": "catPlus",
  "scripts": [
    "blockly/blocks.js",
    "blockly/javascript.js"
  ],
  "dependencies": [
    "gameelements.js"    
  ],
  "msg": "blockly/msg",
  "blocksMsg": "blockly/msg/blocks",
  "toolbox": "blockly/toolbox.xml"
}
